sparkapi/__init__.py
sparkapi/version.json
sparkapi/bin/__init__.py
sparkapi/bin/_chat.py
sparkapi/bin/_image_generation.py
sparkapi/bin/_image_understanding.py
sparkapi/bin/cli.py
sparkapi/config/__init__.py
sparkapi/config/models.json
sparkapi/core/__init__.py
sparkapi/core/chat/__init__.py
sparkapi/core/chat/api.py
sparkapi/core/chat/query.py
sparkapi/core/image_generation/__init__.py
sparkapi/core/image_generation/api.py
sparkapi/core/image_generation/query.py
sparkapi/core/image_understanding/__init__.py
sparkapi/core/image_understanding/api.py
sparkapi/core/image_understanding/query.py
sparkapi/util/__init__.py
sparkapi/util/auth.py
sparkapi/util/common.py
sparkapi_python-1.0.7.dist-info/METADATA
sparkapi_python-1.0.7.dist-info/WHEEL
sparkapi_python-1.0.7.dist-info/entry_points.txt
sparkapi_python-1.0.7.dist-info/top_level.txt
sparkapi_python-1.0.7.dist-info/RECORD
